{
    "boxShadow": "{{appsmith.theme.boxShadow.appBoxShadow}}",
    "mobileBottomRow": 53,
    "widgetName": "Container2",
    "borderColor": "#86efac",
    "isCanvas": true,
    "displayName": "Container",
    "iconSVG": "https://appcdn.appsmith.com/static/media/icon.daebf68875b6c8e909e9e8ac8bee0c02.svg",
    "searchTags": [
        "div",
        "parent",
        "group"
    ],
    "topRow": 55,
    "bottomRow": 71,
    "parentRowSpace": 10,
    "type": "CONTAINER_WIDGET",
    "hideCard": false,
    "shouldScrollContents": true,
    "mobileRightColumn": 24,
    "animateLoading": true,
    "parentColumnSpace": 6.103515625,
    "dynamicTriggerPathList": [],
    "leftColumn": 0,
    "dynamicBindingPathList": [
        {"key": "borderRadius"},
        {"key": "boxShadow"},
        {"key": "backgroundColor"}
    ],
    "children": [{
        "boxShadow": "{{appsmith.theme.boxShadow.appBoxShadow}}",
        "mobileBottomRow": 100,
        "widgetName": "Canvas3",
        "displayName": "Canvas",
        "topRow": 0,
        "bottomRow": 150,
        "parentRowSpace": 1,
        "type": "CANVAS_WIDGET",
        "canExtend": false,
        "hideCard": true,
        "minHeight": 100,
        "mobileRightColumn": 146.484375,
        "parentColumnSpace": 1,
        "leftColumn": 0,
        "dynamicBindingPathList": [
            {"key": "borderRadius"},
            {"key": "boxShadow"}
        ],
        "key": "0va09z4qv6",
        "isDeprecated": false,
        "rightColumn": 146.484375,
        "detachFromLayout": true,
        "dynamicHeight": "AUTO_HEIGHT",
        "widgetId": "c1osqbe2vp",
        "containerStyle": "none",
        "minWidth": 450,
        "isVisible": true,
        "version": 1,
        "parentId": "9nu936glft",
        "renderMode": "CANVAS",
        "isLoading": false,
        "mobileTopRow": 0,
        "responsiveBehavior": "fill",
        "borderRadius": "{{appsmith.theme.borderRadius.appBorderRadius}}",
        "mobileLeftColumn": 0,
        "maxDynamicHeight": 9000,
        "minDynamicHeight": 4,
        "flexLayers": []
    }],
    "borderWidth": "4",
    "flexVerticalAlignment": "stretch",
    "key": "3497m4ehy5",
    "backgroundColor": "{{appsmith.theme.colors.backgroundColor}}",
    "isDeprecated": false,
    "rightColumn": 63,
    "dynamicHeight": "FIXED",
    "widgetId": "9nu936glft",
    "containerStyle": "card",
    "minWidth": 450,
    "isVisible": true,
    "version": 1,
    "parentId": "en1ckz0xx7",
    "tags": ["Layout"],
    "renderMode": "CANVAS",
    "isLoading": false,
    "mobileTopRow": 43,
    "responsiveBehavior": "fill",
    "borderRadius": "{{appsmith.theme.borderRadius.appBorderRadius}}",
    "mobileLeftColumn": 0,
    "maxDynamicHeight": 9000,
    "minDynamicHeight": 10
}