{
    "mobileBottomRow": 63,
    "widgetName": "Text1",
    "displayName": "Text",
    "iconSVG": "https://appcdn.appsmith.com/static/media/icon.a47d6d5dbbb718c4dc4b2eb4f218c1b7.svg",
    "searchTags": [
        "typography",
        "paragraph",
        "label"
    ],
    "topRow": 41,
    "bottomRow": 58,
    "parentRowSpace": 10,
    "type": "TEXT_WIDGET",
    "hideCard": false,
    "mobileRightColumn": 23,
    "animateLoading": true,
    "overflow": "NONE",
    "fontFamily": "{{appsmith.theme.fontFamily.appFont}}",
    "parentColumnSpace": 6.84375,
    "dynamicTriggerPathList": [],
    "leftColumn": 7,
    "dynamicBindingPathList": [
        {"key": "truncateButtonColor"},
        {"key": "fontFamily"},
        {"key": "borderRadius"}
    ],
    "shouldTruncate": false,
    "truncateButtonColor": "{{appsmith.theme.colors.primaryColor}}",
    "text": "Öffnungszeiten:\n6:00 Uhr - 23:00 Uhr\n\nGrößte Verfügbarkeit:\n6:00 Uhr, 23:00 Uhr\n\nGrößte Auslastung:\n12 Uhr - 13 Uhr, 18 Uhr",
    "key": "6tbj8p55mv",
    "isDeprecated": false,
    "rightColumn": 62,
    "textAlign": "LEFT",
    "dynamicHeight": "AUTO_HEIGHT",
    "widgetId": "4cbhuzzeen",
    "minWidth": 450,
    "isVisible": true,
    "fontStyle": "BOLD",
    "textColor": "#86efac",
    "version": 1,
    "parentId": "8374bdsufv",
    "tags": [
        "Suggested",
        "Content"
    ],
    "renderMode": "CANVAS",
    "isLoading": false,
    "mobileTopRow": 59,
    "responsiveBehavior": "fill",
    "originalTopRow": 41,
    "borderRadius": "{{appsmith.theme.borderRadius.appBorderRadius}}",
    "mobileLeftColumn": 7,
    "maxDynamicHeight": 9000,
    "originalBottomRow": 58,
    "fontSize": "1rem",
    "minDynamicHeight": 4
}